work_BH/etc/TEST_systolic/TEST_systolic.srcs/sources_1/imports/systolic_array/processing_element.sv
// Processing Element (PE) module
module processing_element #(
    parameter ARRAY_SIZE = 8,
    parameter DATA_WIDTH = 8
)(
    input  logic                                 clk,
    input  logic                                 rst_n,
    input  logic                                 valid_in,
    input  logic [DATA_WIDTH-1:0]               a_in,
    input  logic [DATA_WIDTH-1:0]               b_in,
    input  logic [DATA_WIDTH*2+ARRAY_SIZE-1:0]  c_in,
    output logic [DATA_WIDTH-1:0]               a_out,
    output logic [DATA_WIDTH-1:0]               b_out,
    output logic [DATA_WIDTH*2+ARRAY_SIZE-1:0]  c_out,
    output logic                                valid_out
);

    // Registered outputs
    always @(posedge clk or negedge rst_n) begin
        if (!rst_n) begin
            a_out <= '0;
            b_out <= '0;
            c_out <= '0;
            valid_out <= 1'b0;
        end else begin
            a_out <= a_in;
            b_out <= b_in;
            // MAC operation using DSP48E1
            c_out <= c_in + (a_in * b_in);
            valid_out <= valid_in;
        end
    end

endmodule

work_BH/etc/TEST_systolic/TEST_systolic.srcs/sources_1/imports/systolic_array/systolic_array.sv
`timescale 1ns / 1ps

// Parameterized Systolic Array for matrix multiplication
// Uses DSP48E1 for MAC operations
module systolic_array #(
    parameter ARRAY_SIZE = 8,    // NxN array size
    parameter DATA_WIDTH = 8     // Input data width
)(
    input  logic                                 clk,
    input  logic                                 rst_n,
    input  logic                                 valid_in,
    input  logic [DATA_WIDTH-1:0]                a_inputs [ARRAY_SIZE-1:0], // Input matrix A
    input  logic [DATA_WIDTH-1:0]                b_inputs [ARRAY_SIZE-1:0], // Input matrix B
    output logic [DATA_WIDTH*2+ARRAY_SIZE-1:0]   c_outputs [ARRAY_SIZE-1:0], // Output matrix C
    output logic                                 valid_out
);

    // Internal signals for PE connections
    logic [DATA_WIDTH-1:0] a_wires [ARRAY_SIZE:0][ARRAY_SIZE:0];
    logic [DATA_WIDTH-1:0] b_wires [ARRAY_SIZE:0][ARRAY_SIZE:0];
    logic [DATA_WIDTH*2+ARRAY_SIZE-1:0] c_wires [ARRAY_SIZE:0][ARRAY_SIZE:0];
    
    // Valid signal propagation
    logic valid_regs [ARRAY_SIZE:0][ARRAY_SIZE:0];
    
    // Input assignment
    always @(posedge clk or negedge rst_n) begin
        if (!rst_n) begin
            for (int i = 0; i < ARRAY_SIZE; i++) begin
                a_wires[0][i] <= '0;
                b_wires[i][0] <= '0;
                valid_regs[0][i] <= '0;
                valid_regs[i][0] <= '0;
            end
        end else begin
            for (int i = 0; i < ARRAY_SIZE; i++) begin
                a_wires[0][i] <= a_inputs[i];
                b_wires[i][0] <= b_inputs[i];
                valid_regs[0][i] <= valid_in;
                valid_regs[i][0] <= valid_in;
            end
        end
    end

    // Generate the PE array
    genvar i, j;
    generate
        for (i = 0; i < ARRAY_SIZE; i++) begin : ROW
            for (j = 0; j < ARRAY_SIZE; j++) begin : COL
                processing_element #(
                    .ARRAY_SIZE(ARRAY_SIZE),
                    .DATA_WIDTH(DATA_WIDTH)
                ) pe (
                    .clk(clk),
                    .rst_n(rst_n),
                    .valid_in(valid_regs[i][j]),
                    .a_in(a_wires[i][j]),
                    .b_in(b_wires[i][j]),
                    .c_in((i == 0 || j == 0) ? 0 : c_wires[i][j]),
                    .a_out(a_wires[i+1][j]),
                    .b_out(b_wires[i][j+1]),
                    .c_out(c_wires[i+1][j]),
                    .valid_out(valid_regs[i+1][j+1])
                );
            end
        end
    endgenerate

    // Output assignment
    always @(posedge clk or negedge rst_n) begin
        if (!rst_n) begin
            for (int i = 0; i < ARRAY_SIZE; i++) begin
                c_outputs[i] <= '0;
            end
            valid_out <= 1'b0;
        end else begin
            for (int i = 0; i < ARRAY_SIZE; i++) begin
                c_outputs[i] <= c_wires[ARRAY_SIZE][i];
            end
            valid_out <= valid_regs[ARRAY_SIZE][ARRAY_SIZE];
        end
    end

endmodule

work_BH/etc/TEST_systolic/TEST_systolic.srcs/sim_1/imports/systolic_array/systolic_array_tb.sv
`timescale 1ns / 1ps

module systolic_array_tb;
    // Parameters
    localparam ARRAY_SIZE = 3;
    localparam DATA_WIDTH = 8;
    localparam CLK_PERIOD = 10;
    
    // Signals
    logic clk;
    logic rst_n;
    logic valid_in;
    logic [DATA_WIDTH-1:0] a_inputs [ARRAY_SIZE-1:0];
    logic [DATA_WIDTH-1:0] b_inputs [ARRAY_SIZE-1:0];
    logic [DATA_WIDTH*2+ARRAY_SIZE-1:0] c_outputs [ARRAY_SIZE-1:0];
    logic valid_out;
    
    // DUT instantiation
    systolic_array #(
        .ARRAY_SIZE(ARRAY_SIZE),
        .DATA_WIDTH(DATA_WIDTH)
    ) dut (.*);
    
    // Clock generation
    initial begin
        clk = 0;
        forever #(CLK_PERIOD/2) clk = ~clk;
    end
    
    // Test stimulus
    initial begin
        // Initialize test matrices
        logic [DATA_WIDTH-1:0] matrix_a [ARRAY_SIZE][ARRAY_SIZE];
        logic [DATA_WIDTH-1:0] matrix_b [ARRAY_SIZE][ARRAY_SIZE];
        
        // Reset
        rst_n = 0;
        valid_in = 0;
        foreach(a_inputs[i]) a_inputs[i] = '0;
        foreach(b_inputs[i]) b_inputs[i] = '0;
        repeat(3) @(posedge clk);
        rst_n = 1;
        
        // Initialize test matrices with simple values
        for (int i = 0; i < ARRAY_SIZE; i++) begin
            for (int j = 0; j < ARRAY_SIZE; j++) begin
                matrix_a[i][j] = ARRAY_SIZE*i + j + 1;
                matrix_b[i][j] = ARRAY_SIZE*i + j + 1;
            end
        end
        
        // Feed the matrices
        valid_in = 1;
        for (int cycle = 0; cycle < ARRAY_SIZE*2; cycle++) begin
            for (int i = 0; i < ARRAY_SIZE; i++) begin
                // Diagonal feeding pattern
                if (cycle - i >= 0 && cycle - i < ARRAY_SIZE) begin
                    a_inputs[i] = matrix_a[i][cycle-i];
                    b_inputs[i] = matrix_b[cycle-i][i];
                end else begin
                    a_inputs[i] = '0;
                    b_inputs[i] = '0;
                end
            end
            @(posedge clk);
        end
        valid_in = 0;
        
        // Wait for computation to complete
        // Need to wait ARRAY_SIZE more cycles for the result to propagate
        repeat(ARRAY_SIZE + 5) @(posedge clk);
        
        // Print results
        $display("Matrix multiplication results:");
        for (int i = 0; i < ARRAY_SIZE; i++) begin
            $write("Row %0d: ", i);
            for (int j = 0; j < ARRAY_SIZE; j++) begin
                $write("%d ", c_outputs[i]);
            end
            $display("");
        end
        
        // End simulation
        #100;
        $finish;
    end
    
    // Optional: Waveform dumping
    initial begin
        $dumpfile("systolic_array_tb.vcd");
        $dumpvars(0, systolic_array_tb);
    end

endmodule

work_BH/etc/TEST_systolic/TEST_systolic.sim/sim_1/behav/xsim/systolic_array_tb.vcd
$date
   Fri Mar 14 21:24:44 2025
$end
$version
  2022.1
$end
$timescale
  1ps
$end
$scope module systolic_array_tb $end
$var reg 1 ! clk $end
$var reg 1 " rst_n $end
$var reg 1 # valid_in $end
$var reg 1 $ valid_out $end
$scope module dut $end
$var wire 1 % clk $end
$var wire 1 & rst_n $end
$var wire 1 ' valid_in $end
$var reg 1 $ valid_out $end
$scope begin Block29_1 $end
$var reg 32 ( i [31:0] $end
$upscope $end
$scope begin Block36_2 $end
$var reg 32 ) i [31:0] $end
$upscope $end
$scope module ROW[0].COL[0].pe $end
$var wire 1 % clk $end
$var wire 1 & rst_n $end
$var wire 1 * valid_in $end
$var wire 8 + a_in [7:0] $end
$var wire 8 , b_in [7:0] $end
$var wire 19 - c_in [18:0] $end
$var reg 8 . a_out [39:32] $end
$var reg 8 / b_out [15:8] $end
$var reg 19 0 c_out [94:76] $end
$var reg 1 1 valid_out $end
$upscope $end
$scope module ROW[0].COL[1].pe $end
$var wire 1 % clk $end
$var wire 1 & rst_n $end
$var wire 1 2 valid_in $end
$var wire 8 3 a_in [7:0] $end
$var wire 8 4 b_in [7:0] $end
$var wire 19 5 c_in [18:0] $end
$var reg 8 6 a_out [47:40] $end
$var reg 8 7 b_out [23:16] $end
$var reg 19 8 c_out [113:95] $end
$var reg 1 9 valid_out $end
$upscope $end
$scope module ROW[0].COL[2].pe $end
$var wire 1 % clk $end
$var wire 1 & rst_n $end
$var wire 1 : valid_in $end
$var wire 8 ; a_in [7:0] $end
$var wire 8 < b_in [7:0] $end
$var wire 19 = c_in [18:0] $end
$var reg 8 > a_out [55:48] $end
$var reg 8 ? b_out [31:24] $end
$var reg 19 @ c_out [132:114] $end
$var reg 1 A valid_out $end
$upscope $end
$scope module ROW[1].COL[0].pe $end
$var wire 1 % clk $end
$var wire 1 & rst_n $end
$var wire 1 B valid_in $end
$var wire 8 C a_in [7:0] $end
$var wire 8 D b_in [7:0] $end
$var wire 19 E c_in [18:0] $end
$var reg 8 F a_out [71:64] $end
$var reg 8 G b_out [47:40] $end
$var reg 19 H c_out [170:152] $end
$var reg 1 I valid_out $end
$upscope $end
$scope module ROW[1].COL[1].pe $end
$var wire 1 % clk $end
$var wire 1 & rst_n $end
$var wire 1 J valid_in $end
$var wire 8 K a_in [7:0] $end
$var wire 8 L b_in [7:0] $end
$var wire 19 M c_in [18:0] $end
$var reg 8 N a_out [79:72] $end
$var reg 8 O b_out [55:48] $end
$var reg 19 P c_out [189:171] $end
$var reg 1 Q valid_out $end
$upscope $end
$scope module ROW[1].COL[2].pe $end
$var wire 1 % clk $end
$var wire 1 & rst_n $end
$var wire 1 R valid_in $end
$var wire 8 S a_in [7:0] $end
$var wire 8 T b_in [7:0] $end
$var wire 19 U c_in [18:0] $end
$var reg 8 V a_out [87:80] $end
$var reg 8 W b_out [63:56] $end
$var reg 19 X c_out [208:190] $end
$var reg 1 Y valid_out $end
$upscope $end
$scope module ROW[2].COL[0].pe $end
$var wire 1 % clk $end
$var wire 1 & rst_n $end
$var wire 1 Z valid_in $end
$var wire 8 [ a_in [7:0] $end
$var wire 8 \ b_in [7:0] $end
$var wire 19 ] c_in [18:0] $end
$var reg 8 ^ a_out [103:96] $end
$var reg 8 _ b_out [79:72] $end
$var reg 19 ` c_out [246:228] $end
$var reg 1 a valid_out $end
$upscope $end
$scope module ROW[2].COL[1].pe $end
$var wire 1 % clk $end
$var wire 1 & rst_n $end
$var wire 1 b valid_in $end
$var wire 8 c a_in [7:0] $end
$var wire 8 d b_in [7:0] $end
$var wire 19 e c_in [18:0] $end
$var reg 8 f a_out [111:104] $end
$var reg 8 g b_out [87:80] $end
$var reg 19 h c_out [265:247] $end
$var reg 1 i valid_out $end
$upscope $end
$scope module ROW[2].COL[2].pe $end
$var wire 1 % clk $end
$var wire 1 & rst_n $end
$var wire 1 j valid_in $end
$var wire 8 k a_in [7:0] $end
$var wire 8 l b_in [7:0] $end
$var wire 19 m c_in [18:0] $end
$var reg 8 n a_out [119:112] $end
$var reg 8 o b_out [95:88] $end
$var reg 19 p c_out [284:266] $end
$var reg 1 q valid_out $end
$upscope $end
$scope begin Block72_13 $end
$var reg 32 r i [31:0] $end
$upscope $end
$scope begin Block77_14 $end
$var reg 32 s i [31:0] $end
$upscope $end
$upscope $end
$scope begin Block31_17 $end
$scope begin Block39_18 $end
$var reg 32 t i [31:0] $end
$upscope $end
$scope begin Block40_19 $end
$var reg 32 u i [31:0] $end
$upscope $end
$scope begin Block45_20 $end
$var reg 32 v i [31:0] $end
$scope begin Block46_21 $end
$var reg 32 w j [31:0] $end
$upscope $end
$upscope $end
$scope begin Block54_22 $end
$var reg 32 x cycle [31:0] $end
$scope begin Block55_23 $end
$var reg 32 y i [31:0] $end
$upscope $end
$upscope $end
$scope begin Block75_24 $end
$var reg 32 z i [31:0] $end
$scope begin Block77_25 $end
$var reg 32 { j [31:0] $end
$upscope $end
$upscope $end
$upscope $end
$upscope $end
$enddefinitions $end
#0
$dumpvars
0!
0"
0#
0$
0%
0&
0'
b11 (
b0 )
0*
b0 +
b0 ,
b0 -
b0 .
b0 /
b0 0
01
02
b0 3
b0 4
b0 5
b0 6
b0 7
b0 8
09
0:
b0 ;
b0 <
b0 =
b0 >
b0 ?
b0 @
0A
0B
b0 C
b0 D
b0 E
b0 F
b0 G
b0 H
0I
0J
b0 K
b0 L
b0 M
b0 N
b0 O
b0 P
0Q
0R
b0 S
b0 T
b0 U
b0 V
b0 W
b0 X
0Y
0Z
b0 [
b0 \
b0 ]
b0 ^
b0 _
b0 `
0a
0b
b0 c
b0 d
b0 e
b0 f
b0 g
b0 h
0i
0j
b0 k
b0 l
b0 m
b0 n
b0 o
b0 p
0q
b11 r
b0 s
b11111111111111111111111111111111 t
b11111111111111111111111111111111 u
b0 v
b0 w
b0 x
b0 y
b0 z
b0 {
$end
#5000
1!
1%
b11 (
b11 r
#10000
0!
0%
#15000
1!
1%
b11 (
b11 r
#20000
0!
0%
#25000
1!
1"
1#
1%
1&
1'
b11 )
1*
b1 +
b1 ,
b0 .
b0 /
01
12
b0 6
b0 7
09
1:
b0 >
b0 ?
0A
1B
b0 F
b0 G
0I
b0 N
b0 O
0Q
b0 V
b0 W
0Y
1Z
b0 ^
b0 _
0a
b0 f
b0 g
0i
b0 n
b0 o
0q
b11 s
b11 v
b11 w
b11 y
#30000
0!
0%
#35000
1!
1%
b11 )
b10 +
b100 ,
b1 .
b1 /
b1 0
11
b100 3
b1 4
b0 6
b0 7
b0 8
19
b0 >
b0 ?
b0 @
1A
b1 C
b10 D
b0 F
b0 G
b0 H
1I
1J
b0 N
b0 O
b0 P
0Q
1R
b0 V
b0 W
b0 X
0Y
b0 ^
b0 _
b0 `
1a
1b
b0 f
b0 g
b0 h
0i
b0 n
b0 o
b0 p
0q
b11 s
b1 x
b11 y
#40000
0!
0%
#45000
1!
1%
b11 )
b11 +
b111 ,
b10 .
b100 /
b1000 0
b101 3
b100 4
b100 6
b1 7
b100 8
b111 ;
b1 <
b0 >
b0 ?
b0 @
b10 C
b101 D
b1 F
b10 G
b10 H
b100 K
b10 L
b100 M
b0 N
b0 O
b0 P
1Q
b0 V
b0 W
b0 X
1Y
b1 [
b11 \
b0 ^
b0 _
b0 `
1a
b0 f
b0 g
b0 h
1i
1j
b0 n
b0 o
b0 p
0q
b11 s
b10 x
b11 y
#50000
0!
0%
#55000
1!
1%
b11 )
b0 +
b0 ,
b11 .
b111 /
b10101 0
b110 3
b111 4
b101 6
b100 7
b10100 8
b1000 ;
b100 <
b111 >
b1 ?
b111 @
b11 C
b1000 D
b10 F
b101 G
b1010 H
b101 K
b101 L
b10100 M
b100 N
b10 O
b1100 P
b111 S
b10 T
b111 U
b0 V
b0 W
b0 X
b10 [
b110 \
b1 ^
b11 _
b11 `
b100 c
b11 d
b1100 e
b0 f
b0 g
b0 h
b0 n
b0 o
b0 p
1q
b11 s
b11 x
b11 y
#60000
0!
0%
#65000
1!
1$
1%
b11 )
b0 .
b0 /
b0 0
b0 3
b0 4
b110 6
b111 7
b101010 8
b1001 ;
b111 <
b1000 >
b100 ?
b100000 @
b0 C
b0 D
b11 F
b1000 G
b11000 H
b110 K
b1000 L
b101010 M
b101 N
b101 O
b101101 P
b1000 S
b101 T
b100000 U
b111 V
b10 W
b10101 X
b11 [
b1001 \
b10 ^
b110 _
b1100 `
b101 c
b110 d
b101101 e
b100 f
b11 g
b11000 h
b111 k
b11 l
b10101 m
b0 n
b0 o
b0 p
b11 s
b100 x
b11 y
#70000
0!
0%
#75000
1!
1%
b11 )
b0 .
b0 /
b0 6
b0 7
b0 8
b0 ;
b0 <
b1001 >
b111 ?
b111111 @
b0 F
b0 G
b0 H
b0 K
b0 L
b0 M
b110 N
b1000 O
b1011010 P
b1001 S
b1000 T
b111111 U
b1000 V
b101 W
b1001000 X
b0 [
b0 \
b11 ^
b1001 _
b11011 `
b110 c
b1001 d
b1011010 e
b101 f
b110 g
b1001011 h
b1000 k
b110 l
b1001000 m
b111 n
b11 o
b101010 p
b11 s
b101 x
b11 y
#80000
0!
0%
#85000
1!
0#
1%
0'
b11 )
0*
11
02
19
0:
b0 >
b0 ?
b0 @
1A
0B
b0 F
b0 G
b0 H
1I
b0 N
b0 O
b0 P
1Q
b0 S
b0 T
b0 U
b1001 V
b1000 W
b10000111 X
1Y
0Z
b0 ^
b0 _
b0 `
1a
b0 c
b0 d
b0 e
b110 f
b1001 g
b10010000 h
1i
b1001 k
b1001 l
b10000111 m
b1000 n
b110 o
b1111000 p
1q
b11 s
b110 x
#90000
0!
0%
#95000
1!
1%
b11 )
01
09
0A
0I
0J
1Q
0R
b0 V
b0 W
b0 X
1Y
b0 ^
b0 _
b0 `
0a
0b
b0 f
b0 g
b0 h
1i
b0 k
b0 l
b0 m
b1001 n
b1001 o
b11011000 p
1q
b11 s
#100000
0!
0%
#105000
1!
1%
b11 )
0Q
0Y
0a
0i
0j
b0 n
b0 o
b0 p
1q
b11 s
#110000
0!
0%
#115000
1!
1%
b11 )
0q
b11 s
#120000
0!
0%
#125000
1!
0$
1%
b11 )
b11 s
#130000
0!
0%
#135000
1!
1%
b11 )
b11 s
#140000
0!
0%
#145000
1!
1%
b11 )
b11 s
#150000
0!
0%
#155000
1!
1%
b11 )
b11 s
#160000
0!
0%
#165000
1!
1%
b11 )
b11 s
b11 z
b11 {
#170000
0!
0%
#175000
1!
1%
b11 )
b11 s
#180000
0!
0%
#185000
1!
1%
b11 )
b11 s
#190000
0!
0%
#195000
1!
1%
b11 )
b11 s
#200000
0!
0%
#205000
1!
1%
b11 )
b11 s
#210000
0!
0%
#215000
1!
1%
b11 )
b11 s
#220000
0!
0%
#225000
1!
1%
b11 )
b11 s
#230000
0!
0%
#235000
1!
1%
b11 )
b11 s
#240000
0!
0%
#245000
1!
1%
b11 )
b11 s
#250000
0!
0%
#255000
1!
1%
b11 )
b11 s
